dis/lab0/example2_1.v
module example2_1(x1, x2, x3, x4, f, g, h);

	input x1, x2, x3, x4;
	output f, g, h;
	
	and (i, x1, x3);
	and (j, x2, x4);
	or (g, i, j);
	
	not (k, x3);
	not (l, x2);
	
	or (m, x1, k);
	or (n, x4, l);
	and (h, m, n);
	
	or (f, g, h);

endmodule

dis/lab0/example2_1_tb.v
`timescale 1ns/1ns
`include "example2_1.v"

module example2_1_tb();
	reg x1, x2, x3, x4;
	wire f, g, h;

	example2_1 ex2_1(x1, x2, x3, x4, f, g, h);
	initial begin

		$dumpfile("example2_1_tb.vcd");
		$dumpvars(0, example2_1_tb);
		
		x1 = 1'b0; x2 = 1'b0; x3 = 1'b0; x4 = 1'b0;
		#20
		
		x1 = 1'b0; x2 = 1'b0; x3 = 1'b0; x4 = 1'b1;
		#20
		
		x1 = 1'b0; x2 = 1'b0; x3 = 1'b1; x4 = 1'b0;
		#20
		
		x1 = 1'b0; x2 = 1'b0; x3 = 1'b1; x4 = 1'b1;
		#20
		
		x1 = 1'b0; x2 = 1'b1; x3 = 1'b0; x4 = 1'b0;
		#20
		
		x1 = 1'b0; x2 = 1'b1; x3 = 1'b0; x4 = 1'b1;
		#20
		
		x1 = 1'b0; x2 = 1'b1; x3 = 1'b1; x4 = 1'b0;
		#20
		
		x1 = 1'b0; x2 = 1'b1; x3 = 1'b1; x4 = 1'b1;
		#20
		
		x1 = 1'b1; x2 = 1'b0; x3 = 1'b0; x4 = 1'b0;
		#20
		
		x1 = 1'b1; x2 = 1'b0; x3 = 1'b0; x4 = 1'b1;
		#20
		
		x1 = 1'b1; x2 = 1'b0; x3 = 1'b1; x4 = 1'b0;
		#20
		
		x1 = 1'b1; x2 = 1'b0; x3 = 1'b1; x4 = 1'b1;
		#20
		
		x1 = 1'b1; x2 = 1'b1; x3 = 1'b0; x4 = 1'b0;
		#20
		
		x1 = 1'b1; x2 = 1'b1; x3 = 1'b0; x4 = 1'b1;
		#20
		
		x1 = 1'b1; x2 = 1'b1; x3 = 1'b1; x4 = 1'b0;
		#20
		
		x1 = 1'b1; x2 = 1'b1; x3 = 1'b1; x4 = 1'b1;
		#20
		
		$display("Test complete");
	
end endmodule

dis/lab0/example2_1_tb.vcd
$date
	Wed Jul 23 23:58:52 2025
$end
$version
	Icarus Verilog
$end
$timescale
	1ns
$end
$scope module example2_1_tb $end
$var wire 1 ! h $end
$var wire 1 " g $end
$var wire 1 # f $end
$var reg 1 $ x1 $end
$var reg 1 % x2 $end
$var reg 1 & x3 $end
$var reg 1 ' x4 $end
$scope module ex2_1 $end
$var wire 1 # f $end
$var wire 1 " g $end
$var wire 1 ! h $end
$var wire 1 ( i $end
$var wire 1 ) j $end
$var wire 1 * k $end
$var wire 1 + l $end
$var wire 1 , m $end
$var wire 1 - n $end
$var wire 1 $ x1 $end
$var wire 1 % x2 $end
$var wire 1 & x3 $end
$var wire 1 ' x4 $end
$upscope $end
$upscope $end
$enddefinitions $end
$comment Show the parameter values. $end
$dumpall
$end
#0
$dumpvars
1-
1,
1+
1*
0)
0(
0'
0&
0%
0$
1#
0"
1!
$end
#20
1'
#40
0#
0!
0,
0*
0'
1&
#60
1'
#80
1,
0-
1*
0+
0'
0&
1%
#100
1#
1"
1!
1)
1-
1'
#120
0#
0"
0!
0,
0)
0-
0*
0'
1&
#140
1#
1"
1)
1-
1'
#160
0"
1!
1*
0)
1+
1,
0'
0&
0%
1$
#180
1'
#200
1"
1(
0*
0'
1&
#220
1'
#240
0#
0!
0"
0-
0(
1*
0+
0'
0&
1%
#260
1#
1"
1!
1)
1-
1'
#280
0!
0)
0-
1(
0*
0'
1&
#300
1!
1)
1-
1'
