dis/lab1/a1.v
module a1(a, b, c, f1, f2);

	input a, b, c;
	output f1, f2;
	
	assign f1 = (a & ~c) | (b & c) | (~b & ~c);
	assign f2 = (a | ~b | c) & (a | b | ~c) & (~a | ~b | ~c);

endmodule

dis/lab1/a1_tb.v
`timescale 1ns/1ns
`include "a1.v"

module a1_tb();
	reg a, b, c;
	wire f1, f2;

	a1 add1(a, b, c, f1, f2);
	initial begin

		$dumpfile("a1_tb.vcd");
		$dumpvars(0, a1_tb);
		
		a = 1'b0; b = 1'b0; c = 1'b0;
		#20
		
		a = 1'b0; b = 1'b0; c = 1'b1;
		#20
		
		a = 1'b0; b = 1'b1; c = 1'b0;
		#20
		
		a = 1'b0; b = 1'b1; c = 1'b1;
		#20
		
		a = 1'b1; b = 1'b0; c = 1'b0;
		#20
		
		a = 1'b1; b = 1'b0; c = 1'b1;
		#20
		
		a = 1'b1; b = 1'b1; c = 1'b0;
		#20
		
		a = 1'b1; b = 1'b1; c = 1'b1;
		#20
		
		$display("Test complete");
	
end endmodule

dis/lab1/a1_tb.vcd
$date
	Wed Jul 23 21:09:45 2025
$end
$version
	Icarus Verilog
$end
$timescale
	1ns
$end
$scope module a1_tb $end
$var wire 1 ! f2 $end
$var wire 1 " f1 $end
$var reg 1 # a $end
$var reg 1 $ b $end
$var reg 1 % c $end
$scope module add1 $end
$var wire 1 # a $end
$var wire 1 $ b $end
$var wire 1 % c $end
$var wire 1 " f1 $end
$var wire 1 ! f2 $end
$upscope $end
$upscope $end
$enddefinitions $end
$comment Show the parameter values. $end
$dumpall
$end
#0
$dumpvars
0%
0$
0#
1"
1!
$end
#20
0!
0"
1%
#40
0!
0%
1$
#60
1"
1!
1%
#80
0%
0$
1#
#100
0"
1%
#120
1"
0%
1$
#140
0!
1%
