dis/lab1/q2_1.v
module q2_1(a, b, c, d, f, g);

	input a, b, c, d;
	output f, g;
	
	nand (i, a, b);
	xor (f, c, d, i);
	nor (g, b, c, d);

endmodule

dis/lab1/q2_1_tb.v
`timescale 1ns/1ns
`include "q2_1.v"

module q2_1_tb();
	reg a, b, c, d;
	wire f, g;

	q2_1 ques2_1(a, b, c, d, f, g);
	initial begin

		$dumpfile("q2_1_tb.vcd");
		$dumpvars(0, q2_1_tb);
		
		a = 1'b0; b = 1'b0; c = 1'b0; d = 1'b0;
		#20
		
		a = 1'b0; b = 1'b0; c = 1'b0; d = 1'b1;
		#20
		
		a = 1'b0; b = 1'b0; c = 1'b1; d = 1'b0;
		#20
		
		a = 1'b0; b = 1'b0; c = 1'b1; d = 1'b1;
		#20
		
		a = 1'b0; b = 1'b1; c = 1'b0; d = 1'b0;
		#20
		
		a = 1'b0; b = 1'b1; c = 1'b0; d = 1'b1;
		#20
		
		a = 1'b0; b = 1'b1; c = 1'b1; d = 1'b0;
		#20
		
		a = 1'b0; b = 1'b1; c = 1'b1; d = 1'b1;
		#20
		
		a = 1'b1; b = 1'b0; c = 1'b0; d = 1'b0;
		#20
		
		a = 1'b1; b = 1'b0; c = 1'b0; d = 1'b1;
		#20
		
		a = 1'b1; b = 1'b0; c = 1'b1; d = 1'b0;
		#20
		
		a = 1'b1; b = 1'b0; c = 1'b1; d = 1'b1;
		#20
		
		a = 1'b1; b = 1'b1; c = 1'b0; d = 1'b0;
		#20
		
		a = 1'b1; b = 1'b1; c = 1'b0; d = 1'b0;
		#20
		
		a = 1'b1; b = 1'b1; c = 1'b0; d = 1'b0;
		#20
		
		a = 1'b1; b = 1'b1; c = 1'b0; d = 1'b0;
		#20
		
		$display("Test complete");
	
end endmodule

dis/lab1/q2_1_tb.vcd
$date
	Wed Jul 23 20:27:42 2025
$end
$version
	Icarus Verilog
$end
$timescale
	1ns
$end
$scope module q2_1_tb $end
$var wire 1 ! g $end
$var wire 1 " f $end
$var reg 1 # a $end
$var reg 1 $ b $end
$var reg 1 % c $end
$var reg 1 & d $end
$scope module ques2_1 $end
$var wire 1 # a $end
$var wire 1 $ b $end
$var wire 1 % c $end
$var wire 1 & d $end
$var wire 1 " f $end
$var wire 1 ! g $end
$var wire 1 ' i $end
$upscope $end
$upscope $end
$enddefinitions $end
$comment Show the parameter values. $end
$dumpall
$end
#0
$dumpvars
1'
0&
0%
0$
0#
1"
1!
$end
#20
0"
0!
1&
#40
0&
1%
#60
1"
1&
#80
0&
0%
1$
#100
0"
1&
#120
0&
1%
#140
1"
1&
#160
1!
0&
0%
0$
1#
#180
0"
0!
1&
#200
0&
1%
#220
1"
1&
#240
0"
0'
0&
0%
1$
